[
  {
    "tibetan": "བཏང་ཐོ",
    "wylie": "btang tho",
    "english": "account (of money or goods) lent or sent out;",
    "russian": "список посланных или данных взаймы (денег, товаров)"
  },
  {
    "tibetan": "ནོར་ཤུལ་ཐོབ་ཐོ",
    "wylie": "nor shul thob tho",
    "english": "list of things which inheritors shall receive;",
    "russian": "опись имущества, которое должны получить наследники"
  },
  {
    "tibetan": "ཞལ་བཀོད་ཐོ་ཡིག",
    "wylie": "zhal bkod tho yig",
    "english": "list of orders or directions given to one;",
    "russian": "список наставлений и приказов, данных кому-л."
  },
  {
    "tibetan": "བཏད་ཐོ",
    "wylie": "btad tho",
    "english": "see བཏང་ཐོ",
    "russian": "см. བཏང་ཐོ"
  },
  {
    "tibetan": "འབྱུང་ཐོ",
    "wylie": "'byung tho",
    "english": "account of receipts;",
    "russian": "список доходов"
  },
  {
    "tibetan": "ཟླ་ཐོ",
    "wylie": "zla tho",
    "english": "calendar, almanac;",
    "russian": "календарь"
  },
  {
    "tibetan": "མེ་ཐོ",
    "wylie": "me tho",
    "english": "see above",
    "russian": "см. выше"
  },
  {
    "tibetan": "ཟིན་ཐོ",
    "wylie": "zin tho",
    "english": "see ཟུར་ཐོ",
    "russian": "см. ཟུར་ཐོ"
  },
  {
    "tibetan": "སྡུད་ཐོ",
    "wylie": "sdud tho",
    "english": "account of receipts.",
    "russian": "список доходов"
  },
  {
    "tibetan": "ཐོ་ཀོར",
    "wylie": "tho kor",
    "english": "see ཐོ་གར",
    "russian": "см. ཐོ་གར"
  },
  {
    "tibetan": "ཐོ་གོར",
    "wylie": "tho gor",
    "english": "see ཐོ་འཁོར",
    "russian": "см. ཐོ་འཁོར"
  },
  {
    "tibetan": "ཐོ་དཀར",
    "wylie": "tho dkar",
    "english": "see ཐོ་གར",
    "russian": "см. ཐོ་གར"
  },
  {
    "tibetan": "ཐོ་འཁོར",
    "wylie": "tho 'khor",
    "english": "neighbourhood; near.",
    "russian": "соседство, близость; близкий, соседний; близко"
  },
  {
    "tibetan": "ཐོ་གར",
    "wylie": "tho gar",
    "english": "1) Tokharistan, ancient Bactria; 2) n. of a race of man.",
    "russian": "1) Тохаристан, древняя Бактрия; 2) назв. народности"
  },
  {
    "tibetan": "ཐོ་མགོ",
    "wylie": "tho mgo",
    "english": "1) halter; 2) (bridle) rein.",
    "russian": "1) недоуздок; 2) повод (для управления лошадью)"
  },
  {
    "tibetan": "ཐོ་ཅོ",
    "wylie": "tho co",
    "english": "1) jokes, jocular talk, nonsense chatter; 2) impudence, shameless; 3) uproar, din.",
    "russian": "1) шутки, шутливый разговор, болтовня; 2) наглость, грубость, бесстыдство; 3) шум, гам"
  },
  {
    "tibetan": "ཐོ་ཆུང",
    "wylie": "tho chung",
    "english": "1) small hammer; 2) cock of a gun.",
    "russian": "1) небольшой молоток; 2) курок"
  },
  {
    "tibetan": "ཐོ་ཐིག",
    "wylie": "tho thig",
    "english": "boundary line.",
    "russian": "пограничная линия, граница"
  },
  {
    "tibetan": "ཐོ་གདན",
    "wylie": "tho gdan",
    "english": "anvil.",
    "russian": "наковальня"
  },
  {
    "tibetan": "ཐོ་རྟེན",
    "wylie": "tho rten",
    "english": "stone boundary mark.",
    "russian": "пограничный камень"
  },
  {
    "tibetan": "ཐོ་དིང",
    "wylie": "tho ding",
    "english": "see ཐོ་ལིང་གི་གཙུག་ལག་ཁང",
    "russian": "см. ཐོ་ལིང་གི་གཙུག་ལག་ཁང"
  },
  {
    "tibetan": "ཐོ་ལོ",
    "wylie": "tho lo",
    "english": "1) the sky. 2) dissimulation.",
    "russian": "1) небо; 2) притворство, обман, лицемерие"
  },
  {
    "tibetan": "ཐོ་ཉེ་དྲུང",
    "wylie": "tho nye drung",
    "english": "near.",
    "russian": "поблизости, вблизи"
  },
  {
    "tibetan": "ཐོ་བ",
    "wylie": "tho ba",
    "english": "hammer, club, mace;",
    "russian": "молот, кувалда, молоток; булава; колотушка, дубинка",
    "sanskrit": "mudgara"
  },
  {
    "tibetan": "རྡོ་ཐོ",
    "wylie": "rdo tho",
    "english": "stone hammer;",
    "russian": "каменный молот"
  },
  {
    "tibetan": "ཤིང་ཐོ",
    "wylie": "shing tho",
    "english": "wooden hammer, mallet.",
    "russian": "деревянный молоток, колотушка"
  },
  {
    "tibetan": "ཐོ་མ",
    "wylie": "tho ma",
    "english": "see above.",
    "russian": "см. выше"
  },
  {
    "tibetan": "ཐོ་འཚམས་པ",
    "wylie": "tho 'tshams pa",
    "english": "1) contempt, scorn; 2) scoffer; 2) to scorn, scoff, jeer.",
    "russian": "1) презрение, насмешка, издёвка, оскорбление; 2) издевающийся, оскорбляющий, насмешник; 2. презирать, глумиться, издеваться, насмехаться, оскорблять",
    "sanskrit": "viheṭanā"
  },
  {
    "tibetan": "ཐོ་ཡོར",
    "wylie": "tho yor",
    "english": "cairn (pyramid of stones heaped up as votive pile).",
    "russian": "обо (ритуальная груда камней, пирамида из камней, как правило, на вершинах гор, перевалах)"
  },
  {
    "tibetan": "ཐོ་རངས",
    "wylie": "tho rangs",
    "english": "1) dawn, break of day, early morning; 2) the following morning, to-morrow.",
    "russian": "1) рассвет, заря, раннее утро; 2) завтрашнее утро, завтра",
    "sanskrit": "prāta, uṣā, pratyuṣa"
  },
  {
    "tibetan": "ཐོ་རུ",
    "wylie": "tho ru",
    "english": "foal.",
    "russian": "жеребёнок"
  },
  {
    "tibetan": "ཐོ་རེ",
    "wylie": "tho re",
    "english": "to-morrow.",
    "russian": "завтра"
  },
  {
    "tibetan": "ཐོ་རེངས",
    "wylie": "tho rengs",
    "english": "see ཐོ་རངས",
    "russian": "см. ཐོ་རངས"
  },
  {
    "tibetan": "ཐོ་རེ་བ",
    "wylie": "tho re ba",
    "english": "1) a little, few, somewhat; 2) see ཐ་རེ་ཐོ་རེ",
    "russian": "1) немного, мало, кое-что; 2) см. ཐ་རེ་ཐོ་རེ"
  },
  {
    "tibetan": "ཐོ་ལོག",
    "wylie": "tho log",
    "english": "religious precepts, moral instruction.",
    "russian": "религиозные принципы, правила морали"
  },
  {
    "tibetan": "ཐོ་ལིང་གི་གཙུག་ལག་ཁང",
    "wylie": "tho ling gi gtsug lag khang",
    "english": "monastery of Tholing.",
    "russian": "монастырь Тхолинг"
  },
  {
    "tibetan": "ཐོ་ལུམ",
    "wylie": "tho lum",
    "english": "kind of hammer with a knob at its head."
  },
  {
    "tibetan": "ཐོ་ལེ",
    "wylie": "tho le",
    "english": "1) projection; ཐོ་ལེ་འདེབས་པ to spit."
  },
  {
    "tibetan": "ཐོ་བུ",
    "wylie": "tho bu",
    "english": "1) button; 2) prominence; ཐོ་བེར་འབུར་བ projected.",
    "russian": "1) пуговица; 2) выступ, выдающаяся часть; ཐོ་བེར་འབུར་བ выступающий, выдающийся"
  }
]