[
  {
    "continued_from_prev_page": true,
    "english": "war materials; weapon; དམག་མཚོན་དང་མཚོན་ཆ་ལྡན་པའི་རྒྱལ་ཁབ a state which possessed full of war materials and weapon.",
    "russian": "териалы; оружие; དམག་མཚོན་དང་མཚོན་ཆ་ལྡན་པའི་རྒྱལ་ཁབ государство, в полной мере располагающее военными материалами и оружием."
  },
  {
    "tibetan": "དམག་འཛོམས",
    "wylie": "dmag 'dzoms",
    "english": "mobilization.",
    "russian": "воен. мобилизация"
  },
  {
    "tibetan": "དམག་ཞྭ",
    "wylie": "dmag zhwa",
    "english": "helmet.",
    "russian": "шлем"
  },
  {
    "tibetan": "དམག་ཟིང",
    "wylie": "dmag zing",
    "english": "war time; troubled times.",
    "russian": "военная година; смутное время"
  },
  {
    "tibetan": "དམག་ཟོར་རྒྱལ་པོ",
    "wylie": "dmag zor rgyal po",
    "russian": "см. དམག་ཟོར་མ."
  },
  {
    "tibetan": "དམག་ཟློག",
    "wylie": "dmag zlog",
    "russian": "см. དམག་བཟློག"
  },
  {
    "tibetan": "དམག་བཟློག",
    "wylie": "dmag bzlog",
    "english": "ceremonial service for disappearing or vanishing war."
  },
  {
    "tibetan": "དམག་རྭ",
    "wylie": "dmag rwa",
    "english": "1) entrenchment; battle-front; 2) military encampment.",
    "russian": "1) окоп, траншея; передовые позиции; 2) военный лагерь"
  },
  {
    "tibetan": "དམག་རུ",
    "wylie": "dmag ru",
    "english": "battalion; brigade.",
    "russian": "батальон; бригада"
  },
  {
    "tibetan": "དམག་རུ་བཅུག་པ",
    "wylie": "dmag ru bcug pa",
    "english": "to attack from two sides.",
    "russian": "атаковать с двух сторон; брать в клещи"
  },
  {
    "tibetan": "དམག་རུམ",
    "wylie": "dmag rum",
    "english": "darkness; དམག་རུམ་སེལ་མཛད་པ to destroy the darkness.",
    "russian": "тьма; དམག་རུམ་སེལ་མཛད་པ разгонять тьму"
  },
  {
    "tibetan": "དམག་རོགས",
    "wylie": "dmag rogs",
    "english": "1) war ally; 2) reinforcement; དམག་རོགས་བྱེད་པ a) to become ally; b) to reinforce.",
    "russian": "1) военный союзник; 2) воен. подкрепление; དམག་རོགས་བྱེད་པ а) становиться союзником; б) воен. усиливать, подкреплять"
  },
  {
    "tibetan": "དམག་ལས",
    "wylie": "dmag las",
    "english": "military affairs; དམག་ལས་ཇུས་དཔོན military adviser; དམག་ལས་རྟེན་གཞི military base; དམག་ལས་དོ་དམ་ལུ་ཡོན་ལྷན་ཁང the Committee of military control.",
    "russian": "военное дело; དམག་ལས་ཇུས་དཔོན военный советник; དམག་ལས་རྟེན་གཞི военная база; དམག་ལས་དོ་དམ་ལུ་ཡོན་ལྷན་ཁང военно-контрольный комитет"
  },
  {
    "tibetan": "དམག་ལོག་རྒྱག",
    "wylie": "dmag log rgyag",
    "english": "counter-attack; counter-offensive.",
    "russian": "контратака; контрнаступление"
  },
  {
    "tibetan": "དམག་ཤུགས",
    "wylie": "dmag shugs",
    "english": "war forces.",
    "russian": "военные силы"
  },
  {
    "tibetan": "དམག་ཤེད",
    "wylie": "dmag shed",
    "english": "militarists, military clique; དམག་ཤེད་ཅན militarist.",
    "russian": "военщина; དམག་ཤེད་ཅན милитаристский"
  },
  {
    "tibetan": "དམག་ཤོར་བ",
    "wylie": "dmag shor ba",
    "english": "defeat.",
    "russian": "воен. поражение"
  },
  {
    "tibetan": "དམག་ས",
    "wylie": "dmag sa",
    "english": "the theatre of war, front.",
    "russian": "театр военных действий, фронт"
  },
  {
    "tibetan": "དམག་ས་མདུན་མ",
    "wylie": "dmag sa mdun ma",
    "english": "the battle-front.",
    "russian": "передовая линия"
  },
  {
    "tibetan": "དམག་སའི་བར་དུ་ཆོད་པའི་རྒྱལ་ཁབ",
    "wylie": "dmag sa'i bar du chod pa'i rgyal khab",
    "english": "buffer state.",
    "russian": "буферное государство"
  },
  {
    "tibetan": "དམག་སྲིད",
    "wylie": "dmag srid",
    "english": "war and policy; Army political.",
    "russian": "война и политика; военно-политический"
  },
  {
    "tibetan": "དམངས",
    "wylie": "dmangs",
    "english": "mob; the common people; subjects.",
    "russian": "толпа; простой люд; подданные"
  },
  {
    "tibetan": "དམངས་ཀྱི་བུད་མེད",
    "wylie": "dmangs kyi bud med",
    "english": "woman belonging to the common people.",
    "russian": "женщина из простонародья"
  },
  {
    "tibetan": "དམངས་ཀྱི་སྟོན་མོ",
    "wylie": "dmangs kyi ston mo",
    "english": "festival for the common people.",
    "russian": "празднество, [устроенное] для простого народа"
  },
  {
    "tibetan": "དམངས་ཆང",
    "wylie": "dmangs chang",
    "english": "\"bear for the common people\" (bear which is given to the common people at entertainments).",
    "russian": "\"пиво для народа\" (пиво, которым угощают простой народ на увеселениях)"
  },
  {
    "tibetan": "དམངས་དོན",
    "wylie": "dmangs don",
    "english": "civil case.",
    "russian": "юр. гражданское дело"
  },
  {
    "tibetan": "དམངས་འཐུས་གྲོང་ཁྱེར",
    "wylie": "dmangs 'thus grong khyer",
    "english": "poet. town, city.",
    "russian": "поэт. город"
  },
  {
    "tibetan": "དམངས་ཐུག",
    "wylie": "dmangs thug",
    "english": "kind of broth or gruel.",
    "russian": "разновидность супа, кашицы"
  },
  {
    "tibetan": "དམངས་ཕལ",
    "wylie": "dmangs phal",
    "english": "the common people.",
    "russian": "простой народ"
  },
  {
    "tibetan": "དམངས་སྲིད",
    "wylie": "dmangs srid",
    "english": "civil; དམངས་སྲིད་མཁའ་འགྲུལ་ལས་ཁུངས civil air transport; དམངས་སྲིད་གནམ་གྲུ civil aviation; དམངས་སྲིད་གྲུ་གཟིངས passenger-ship.",
    "russian": "гражданский; དམངས་སྲིད་མཁའ་འགྲུལ་ལས་ཁུངས гражданский воздушный флот; དམངས་སྲིད་གནམ་གྲུ гражданская авиация; དམངས་སྲིད་གྲུ་གཟིངས пассажирский пароход"
  }
]