[
  {
    "tibetan": " བརྡབ་པ I",
    "wylie": " brdab pa I",
    "english": " past tense བརྡབས 1) to fold; 2) to place together; སྣོད་བརྡབ་པ to put one vessel on another; to place one vessel in another; 3) to clap (one hand against another).",
    "russian": " прош. вр. བརྡབས 1) складывать, сгибать; 2) складывать вместе; སྣོད་བརྡབ་པ ставить один сосуд на другой; вкладывать один сосуд в другой; 3) хлопать (в ладоши)."
  },
  {
    "tibetan": " བརྡབ་པ II",
    "wylie": " brdab pa II",
    "english": " to fall down, to go down; to sink.",
    "russian": " падать; обрушиваться; проваливаться; тонуть"
  },
  {
    "tibetan": " བརྡབས",
    "wylie": " brdabs",
    "english": " past of བརྡབ་པ I.",
    "russian": " прош. вр. от བརྡབ་པ I."
  },
  {
    "tibetan": " བརྡབས་བསིགས",
    "wylie": " brdabs bsigs",
    "english": " oppression, tyranny; giving trouble to the subjects.",
    "russian": " угнетение, тирания"
  },
  {
    "tibetan": " བརྡས་སམ",
    "wylie": " brdas sam",
    "english": " numerical figure",
    "russian": " назв. числа",
    "sanskrit": " samjñā"
  },
  {
    "tibetan": " བརྡས་སམ་ཆེན་པོ",
    "wylie": " brdas sam chen po",
    "english": " number of higher value than the preceding.",
    "russian": " назв. большего числа",
    "sanskrit": " sahasamjñā"
  },
  {
    "tibetan": " བརྡ་ཤུགས",
    "wylie": " brda shugs",
    "english": " words of respect; mutterings expressive respect (in bowing down).",
    "russian": " слова почтения; почтительные выражения (во время поклона)"
  },
  {
    "tibetan": " བརྡ་སློབ",
    "wylie": " brda slob",
    "english": " is stated to be a lama who instructs, verbally esp. with regard to the spelling of words."
  },
  {
    "tibetan": " བརྡར",
    "wylie": " brdar",
    "english": " a symbol, symbolically",
    "russian": " символически"
  },
  {
    "tibetan": " བརྡར་བཏགས་པ",
    "wylie": " brdar btags pa",
    "english": " symbolical.",
    "russian": " символический"
  },
  {
    "tibetan": " བརྡར་བ",
    "wylie": " brdar ba",
    "english": " to sharpen.",
    "russian": " точить, острить"
  },
  {
    "tibetan": " བརྡར་སྦྱོང",
    "wylie": " brdar sbyong",
    "english": " training; བརྡར་སྦྱོང་དཔུང་ཁག training battalion.",
    "russian": " тренировка, обучение; བརྡར་སྦྱོང་དཔུང་ཁག воен. учебная часть"
  },
  {
    "tibetan": " བརྡར་ཤ་ཆོད་པ",
    "wylie": " brdar sha chod pa",
    "english": " decided.",
    "russian": " отбросивший сомнения; решительный"
  },
  {
    "tibetan": " བརྡལ",
    "wylie": " brdal",
    "russian": " прош. и буд. вр. от རྡལ་བ"
  },
  {
    "tibetan": " བརྡིག",
    "wylie": " brdig",
    "russian": " буд. вр. от རྡིག་པ"
  },
  {
    "tibetan": " བརྡིགས",
    "wylie": " brdigs",
    "russian": " прош. вр. от རྡིག་པ"
  },
  {
    "tibetan": " བརྡུང",
    "wylie": " brdung",
    "russian": " буд. вр. от རྡུང་བ"
  },
  {
    "tibetan": " བརྡུངས",
    "wylie": " brdungs",
    "russian": " прош. вр. от རྡུང་བ"
  },
  {
    "tibetan": " བརྡུལ་བ I",
    "wylie": " brdul ba I",
    "english": " to deceive; to cheat.",
    "russian": " обманывать; плутовать"
  },
  {
    "tibetan": " བརྡུལ་བ II",
    "wylie": " brdul ba II",
    "english": " to swing, to brandish, to flourish.",
    "russian": " махать, размахивать"
  },
  {
    "tibetan": " བརྡེག",
    "wylie": " brdeg",
    "russian": " буд. вр. от རྡེག་པ"
  },
  {
    "tibetan": " བརྡེག་ཆ",
    "wylie": " brdeg cha",
    "english": " weapon; sword.",
    "russian": " оружие; меч"
  },
  {
    "tibetan": " བརྡེག་འཆའ་བ",
    "wylie": " brdeg 'cha' ba",
    "russian": " см. བརྡེག་འཆོས་པ II."
  },
  {
    "tibetan": " བརྡེག་འཆོས་པ I",
    "wylie": " brdeg 'chos pa I",
    "english": " to threaten to beat; to prepare to beat.",
    "russian": " угрожать побоями; приготовляться бить"
  },
  {
    "tibetan": " བརྡེག་འཆོས་པ II",
    "wylie": " brdeg 'chos pa II",
    "english": " to slide, to lose one's footing; to fall down.",
    "russian": " поскользнуться; падать"
  },
  {
    "tibetan": " བརྡེགས",
    "wylie": " brdegs",
    "russian": " прош. вр. от རྡེག་པ"
  },
  {
    "tibetan": " བརྡོབ",
    "wylie": " brdob",
    "russian": " прош. и буд. вр. от རྡོབ་པ"
  },
  {
    "tibetan": " བརྡོལ་གཏམ",
    "wylie": " brdol gtam",
    "english": " confused talk; delirium.",
    "russian": " бессвязная (беспорядочная) речь; бред"
  },
  {
    "tibetan": " བརྡོས་ཐབས་སྨྲ་བ",
    "wylie": " brdos thabs smra ba",
    "english": " see above.",
    "russian": " см. выше"
  },
  {
    "tibetan": " བལྡག",
    "wylie": " bldag",
    "russian": " буд. вр. от ལྡག་པ"
  },
  {
    "tibetan": " བལྡགས",
    "wylie": " bldags",
    "russian": " прош. вр. от ལྡག་པ"
  },
  {
    "tibetan": " བལྡད",
    "wylie": " bldad",
    "russian": " прош. и буд. вр. от ལྡད་པ I."
  },
  {
    "tibetan": " བལྡབ",
    "wylie": " bldab",
    "russian": " буд. вр. от ལྡབ་པ"
  },
  {
    "tibetan": " བལྡབས",
    "wylie": " bldabs",
    "russian": " прош. вр. от ལྡབ་པ"
  },
  {
    "tibetan": " བལྡེ",
    "wylie": " blde",
    "russian": " буд. вр. от ལྡེ་བ II."
  },
  {
    "tibetan": " བལྡེག I",
    "wylie": " bldeg I",
    "english": " to quake, to shake, to tremble.",
    "russian": " прош. вр. བལྡེགས трястись, сотрясаться, дрожать"
  },
  {
    "tibetan": " བལྡེག II",
    "wylie": " bldeg II",
    "english": " to bite.",
    "russian": " прош. вр. བལྡེགས кусать(ся)"
  },
  {
    "tibetan": " བལྡེབས",
    "wylie": " bldebs",
    "russian": " прош. вр. от ལྡེབ་པ I, II."
  },
  {
    "tibetan": " བལྡེར",
    "wylie": " blder",
    "russian": " прош. и буд. вр. от ལྡེར་བ"
  },
  {
    "tibetan": " བལྡོག",
    "wylie": " bldog",
    "russian": " буд. вр. от ལྡོག་པ"
  },
  {
    "tibetan": " བལྡོབ",
    "wylie": " bldob",
    "english": " knot.",
    "russian": " узел"
  },
  {
    "tibetan": " བལྡོབས",
    "wylie": " bldobs",
    "russian": " прош. вр. от ལྡོབ་པ"
  },
  {
    "tibetan": " བལྡོས I",
    "wylie": " bldos I",
    "english": " to fear, to dread.",
    "russian": " бояться, страшиться"
  }
]