[
  {
    "continued_from_prev_page": true,
    "english": " to exhibit a mystic symbol; ཕྱག་རྒྱ་ཆེན་པོ mahāmudrā \"great symbol\" (n. of a Tantric initiation); ཕྱག་རྒྱ་ཆེན་པོ་ལྔ་བཅུ་པ་ mahā-mudrā-pañcaśikha; ཕྱག་རྒྱ་ཡོངས་སུ་འཛིན་པ་ཞེས་བྱ་བའི་ཏིང་ངེ་འཛིན ādharaṇamudrā-nāma-samādhi n. of a samādhi; ཕྱག་རྒྱས་འགྲོལ་བ to set evil spirits free by dissolving the charm; ཕྱག་རྒྱས་མནན་པ to overcome evil spirits with mystical signs.",
    "russian": " одну из мудр; ཕྱག་རྒྱ་ཆེན་པོ mahāmudrā \"великий символ\" (назв. одного из важнейших посвящений в буддийском тантризме); ཕྱག་རྒྱ་ཆེན་པོ་ལྔ་བཅུ་པ་ mahā-mudrā-pañcaśikha; ཕྱག་རྒྱ་ཡོངས་སུ་འཛིན་པ་ཞེས་བྱ་བའི་ཏིང་ངེ་འཛིན ādharaṇamudrā-nāma-samādhi назв. одной из разновидностей самадхи; ཕྱག་རྒྱས་འགྲོལ་བ освобождать злых духов, прекращая действие магических жестов; ཕྱག་རྒྱས་མནན་པ подавлять злых духов магическими жестами."
  },
  {
    "tibetan": " ཕྱག་ལྗོན",
    "wylie": " phyag ljon",
    "english": " poet. the mangoe tree.",
    "russian": " поэт. манговое дерево."
  },
  {
    "tibetan": " ཕྱག་རྒྱ་མ",
    "wylie": " phyag rgya ma",
    "english": " buddh. n. of one of śakties.",
    "russian": " будд. назв. одной из шакти.",
    "sanskrit": " śakti; karmamudrā"
  },
  {
    "tibetan": " ཕྱག་རྒྱུན",
    "wylie": " phyag rgyun",
    "english": " see ཕྱག་ལེན",
    "russian": " см. ཕྱག་ལེན"
  },
  {
    "tibetan": " ཕྱག་ངར",
    "wylie": " phyag ngar",
    "english": " the wrist.",
    "russian": " запястье."
  },
  {
    "tibetan": " ཕྱག་ཆ",
    "wylie": " phyag cha",
    "english": " hon. implements, tools.",
    "russian": " почт. инструменты, орудия труда."
  },
  {
    "tibetan": " ཕྱག་ཆུ",
    "wylie": " phyag chu",
    "english": " water for washing the hands.",
    "russian": " вода для мытья рук."
  },
  {
    "tibetan": " ཕྱག་ཆས",
    "wylie": " phyag chas",
    "english": " 1) tools; 2) buddh. attributes carried in the hand (or used in performing religious dances).",
    "russian": " 1) инструменты; 2) будд. предметы-символы, которые держат в руке (при исполнении религиозных танцев)."
  },
  {
    "tibetan": " ཕྱག་ཆེན",
    "wylie": " phyag chen",
    "english": " see ཕྱག་རྒྱ་ཆེན་པོ",
    "russian": " см. ཕྱག་རྒྱ་ཆེན་པོ"
  },
  {
    "tibetan": " ཕྱག་མཆོད",
    "wylie": " phyag mchod",
    "english": " ཕྱག་དང་མཆོད་པ salutation and worship (offering); ཕྱག་མཆོད་བྱེད་པ to salute and worship; ཕྱག་མཆོད་གནང་བ hon. see above.",
    "russian": " ཕྱག་དང་མཆོད་པ приветствие и поклонение (подношение); ཕྱག་མཆོད་བྱེད་པ приветствовать и поклоняться; ཕྱག་མཆོད་གནང་བ почт. см. выше."
  },
  {
    "tibetan": " ཕྱག་མཇལ",
    "wylie": " phyag mjal",
    "english": " interview; ཕྱག་མཇལ་ལ་བཅར་བ to come for interview; ཕྱག་མཇལ་གནང་བ to interview.",
    "russian": " свидание, встреча, беседа; ཕྱག་མཇལ་ལ་བཅར་བ приходить на встречу, беседу; ཕྱག་མཇལ་གནང་བ встречаться, иметь беседу."
  },
  {
    "tibetan": " ཕྱག་རྗེས",
    "wylie": " phyag rjes",
    "english": " 1) hon. a work which immortalizes a person's name; 2) hon. practice.",
    "russian": " 1) почт. славные деяния (подвиги); 2) почт. практика; реализация."
  },
  {
    "tibetan": " ཕྱག་སྙིགས",
    "wylie": " phyag snyigs",
    "english": " rubbish, refuse.",
    "russian": " отбросы; мусор."
  },
  {
    "tibetan": " ཕྱག་བརྙན",
    "wylie": " phyag brnyan",
    "english": " hon. servant; attendants, retinue.",
    "russian": " почт. слуга; сопровождение, свита.",
    "sanskrit": " parivāra, parisara, pariṣada"
  },
  {
    "tibetan": " ཕྱག་གཏོང",
    "wylie": " phyag gtong",
    "english": " hon. handshake; ཕྱག་གཏོང་གནང་བ to shake hands (with).",
    "russian": " почт. рукопожатие; ཕྱག་གཏོང་གནང་བ обмениваться рукопожатиями."
  },
  {
    "tibetan": " ཕྱག་བཏགས",
    "wylie": " phyag btags",
    "english": " hon. present, gift.",
    "russian": " почт. подарок, подношение."
  },
  {
    "tibetan": " ཕྱག་ཐེགས་པ",
    "wylie": " phyag thegs pa",
    "english": " to set off, to go away; to come, to arrive.",
    "russian": " отправляться в путь, уходить; приходить, прибывать."
  },
  {
    "tibetan": " ཕྱག་རྟགས",
    "wylie": " phyag rtags",
    "english": " 1) hon. impression of a finger; seal; signature; 2) hon. present, gift.",
    "russian": " 1) почт. оттиск пальца; печать; подпись; 2) почт. подарок, дар."
  },
  {
    "tibetan": " ཕྱག་རྟེན",
    "wylie": " phyag rten",
    "english": " hon. present, gift; ཕྱག་རྟེན་འབུལ་བ to make a present.",
    "russian": " почт. подарок, дар, подношение; ཕྱག་རྟེན་འབུལ་བ делать подарок.",
    "sanskrit": " upagrahya, pradeśana, sandeśa, upagraha"
  },
  {
    "tibetan": " ཕྱག་བརྟེན",
    "wylie": " phyag brten",
    "english": " see above.",
    "russian": " см. выше."
  },
  {
    "tibetan": " ཕྱག་ཐེལ",
    "wylie": " phyag thel",
    "english": " hon. impression of a finger; seal.",
    "russian": " почт. отпечаток пальца; печать."
  },
  {
    "tibetan": " ཕྱག་མཐིལ",
    "wylie": " phyag mthil",
    "english": " hon. palm of the hand.",
    "russian": " почт. ладонь."
  },
  {
    "tibetan": " ཕྱག་མཐེབ",
    "wylie": " phyag mtheb",
    "english": " hon. the thumb.",
    "russian": " почт. большой палец (руки)."
  },
  {
    "tibetan": " ཕྱག་དྲེག་བསིལ་བ",
    "wylie": " phyag dreg bsil ba",
    "english": " hon. to wash one's hands.",
    "russian": " почт. мыть руки."
  }
]