[
  {
    "continued_from_prev_page": true,
    "tibetan": " སྐྱེས་སུ་དབུལ་བ",
    "wylie": " skyes su dbul ba",
    "english": " to present; to accept as a present.",
    "russian": " рить; принять в качестве подарка"
  },
  {
    "tibetan": " སྐྱེས་སྐར",
    "wylie": " skyes skar",
    "english": " birthday.",
    "russian": " день рождения"
  },
  {
    "tibetan": " སྐྱེས་སྐུར་བ",
    "wylie": " skyes skur ba",
    "english": " to give a present; to send a present.",
    "russian": " подносить подарок; посылать подарок"
  },
  {
    "tibetan": " སྐྱེས་པ",
    "wylie": " skyes pa",
    "english": " present;",
    "russian": " подарок;"
  },
  {
    "tibetan": " སྐྱེས་པ་གནང་བ",
    "wylie": " skyes pa gnang ba",
    "english": " to give a present.",
    "russian": " подносить подарок"
  },
  {
    "tibetan": " སྐྱེས་སྦྱར",
    "wylie": " skyes sbyar",
    "english": " poet. billy-goat.",
    "russian": " поэт. козёл"
  },
  {
    "tibetan": " སྐྱེས་ཆང་",
    "wylie": " skyes chang",
    "english": " present of beer.",
    "russian": " пиво, поднесённое в подарок"
  },
  {
    "tibetan": " སྐྱེས་ཆེན",
    "wylie": " skyes chen",
    "english": " I great man; holy person;",
    "russian": " I великий человек; святой, отшельник"
  },
  {
    "tibetan": " སྐྱེས་ཆེན་སྒྲུབ་ཁང",
    "wylie": " skyes chen sgrub khang",
    "english": " hermitage of a holy person;",
    "russian": " жилище отшельника"
  },
  {
    "tibetan": " སྐྱེས་ཆེན་དམ་པ",
    "wylie": " skyes chen dam pa",
    "english": " great saint;",
    "russian": " великий святой"
  },
  {
    "tibetan": " སྐྱེས་ཆེན་འདས་པ",
    "wylie": " skyes chen 'das pa",
    "english": " to pass away, to decease.",
    "russian": " скончаться, преставиться"
  },
  {
    "tibetan": " སྐྱེས་ཆེན",
    "wylie": " skyes chen",
    "english": " II present sent with a letter.",
    "russian": " II подарок, посылаемый с письмом"
  },
  {
    "tibetan": " སྐྱེས་འཆི",
    "wylie": " skyes 'chi",
    "english": " birth and death;",
    "russian": " рождение и смерть"
  },
  {
    "tibetan": " སྐྱེས་འཆི་མེད་པ",
    "wylie": " skyes 'chi med pa",
    "english": " without birth or death, eternal.",
    "russian": " не имеющий рождения и смерти, вечный"
  },
  {
    "tibetan": " སྐྱེས་དུས",
    "wylie": " skyes dus",
    "english": " the last month of pregnancy.",
    "russian": " последний месяц беременности",
    "sanskrit": " vaijanana"
  },
  {
    "tibetan": " སྐྱེས་བདག",
    "wylie": " skyes bdag",
    "english": " n. of the fifth year of the 60-years cycle.",
    "russian": " название пятого года шестидесятилетнего цикла",
    "sanskrit": " prajāpati"
  },
  {
    "tibetan": " སྐྱེས་ལྡན",
    "wylie": " skyes ldan",
    "english": " animate being.",
    "russian": " одушевлённое существо"
  },
  {
    "tibetan": " སྐྱེས་ནག",
    "wylie": " skyes nag",
    "english": " 1) see སྐྱེས་བུ་ནག་པོ།; 2) widower.",
    "russian": " 1) см. སྐྱེས་བུ་ནག་པོ།; 2) вдовец"
  },
  {
    "tibetan": " སྐྱེས་སྤྲོད",
    "wylie": " skyes sprod",
    "english": " n. of a measure used by creditors in receiving back the loan of grain.",
    "russian": " название мерки, которой пользуются заимодавцы, получая зерно от должника"
  },
  {
    "tibetan": " སྐྱེས་ཕམ",
    "wylie": " skyes pham",
    "english": " maiden.",
    "russian": " девица, девушка",
    "sanskrit": " yuvati"
  },
  {
    "tibetan": " སྐྱེས་ཕོ",
    "wylie": " skyes pho",
    "english": " man, male.",
    "russian": " мужчина"
  },
  {
    "tibetan": " སྐྱེས་ཕྲན་བ",
    "wylie": " skyes phran ba",
    "english": " 1) person in the prime of life; 2) boy.",
    "russian": " 1) человек в расцвете сил; 2) мальчик; юноша"
  },
  {
    "tibetan": " སྐྱེས་འཕྲེང",
    "wylie": " skyes 'phreng",
    "english": " birth chain, successive incarnations.",
    "russian": " цепь перерождений",
    "sanskrit": " jātaka"
  },
  {
    "tibetan": " སྐྱེས་བུ",
    "wylie": " skyes bu",
    "english": " I human being; man, individual;",
    "russian": " I человек, мужчина; человеческое существо, личность",
    "sanskrit": " puruṣa"
  },
  {
    "tibetan": " སྐྱེས་བུ་སྐྱེས་མཆོག",
    "wylie": " skyes bu skyes mchog",
    "english": " the best among men; the chief among men;",
    "russian": " лучший среди людей; главный среди людей",
    "sanskrit": " puruṣapuṃgava"
  },
  {
    "tibetan": " སྐྱེས་བུ་ཁྱུ་མཆོག",
    "wylie": " skyes bu khyu mchog",
    "english": " leader of men;",
    "russian": " вождь, лидер",
    "sanskrit": " puruṣaurṣabha"
  },
  {
    "tibetan": " སྐྱེས་བུ་ཅན",
    "wylie": " skyes bu can",
    "english": " horseman;",
    "russian": " всадник"
  },
  {
    "tibetan": " སྐྱེས་བུ་ཆུང་ངུ",
    "wylie": " skyes bu chung ngu",
    "english": " buddh. ordinary wordly being, individual of the lowest order;",
    "russian": " будд. простой смертный, заурядный человек (одна из трёх категорий людей, на которые делится человечество по отношению к внешнему феноменальному миру и к пути спасения)",
    "sanskrit": " adhama-puruṣa"
  },
  {
    "tibetan": " སྐྱེས་བུ་ཆེན་པོ",
    "wylie": " skyes bu chen po",
    "english": " \"Great man\" (epith. of Buddha);",
    "russian": " \"Великое существо\" (эпит. Будды)",
    "sanskrit": " mahāpuruṣa"
  },
  {
    "tibetan": " སྐྱེས་བུ་ཆེན་པོའི་མཚན",
    "wylie": " skyes bu chen po'i mtshan",
    "english": " buddh. the [32] marks of a superman;",
    "russian": " будд. [32] признака великого существа",
    "sanskrit": " mahāpuruṣalakṣaṇa"
  },
  {
    "tibetan": " སྐྱེས་བུ་མཆོག",
    "wylie": " skyes bu mchog",
    "english": " \"Superior person\" (epith. of Viṣṇu);",
    "russian": " \"Высшее существо\" (эпит. Вишну)",
    "sanskrit": " puruṣottama"
  },
  {
    "tibetan": " སྐྱེས་བུ་བཏགས་ཡོད་ཀྱི་རྣམ་པར་རྟོག་པ",
    "wylie": " skyes bu btags yod kyi rnam par rtog pa",
    "english": " buddh. the imputation regarding subject as a nominal reality;",
    "russian": " будд. представление о субъекте как о номинально-реальной личности",
    "sanskrit": " prajñaptisatpuruṣādhiṣṭhānagrahakavikalpa"
  },
  {
    "tibetan": " སྐྱེས་བུ་བརྟག་པ",
    "wylie": " skyes bu brtag pa",
    "english": " investigation of the reality of \"self\";",
    "russian": " исследование реальности \"я\"",
    "sanskrit": " puruṣaparīkṣa"
  },
  {
    "tibetan": " སྐྱེས་བུ་མཐོ",
    "wylie": " skyes bu mtho",
    "english": " myth. n. of a tree growing in",
    "russian": " миф. назв. дерева, растущего в стране нагов",
    "continues_next_page": true
  }
]