[
  {
    "continued_from_prev_page": true,
    "english": "gold coin; an ounce of gold.",
    "russian": "одна унция золота"
  },
  {
    "tibetan": "གསེར་ལྷད་ཅན",
    "wylie": "gser lhad can",
    "english": "alloyed gold.",
    "russian": "лигатурное золото"
  },
  {
    "tibetan": "གསེས",
    "wylie": "gses",
    "english": "reciprocal, mutual.",
    "russian": "взаимный, обоюдный"
  },
  {
    "tibetan": "གསེས་པ",
    "wylie": "gses pa",
    "english": "split.",
    "russian": "расколотый, расщеплённый",
    "sanskrit": "dārita"
  },
  {
    "tibetan": "གསེས",
    "wylie": "gses",
    "english": "difference; sort; kind; order.",
    "russian": "II различие; сорт; класс, разряд; порядок, последовательность"
  },
  {
    "tibetan": "གསོ",
    "wylie": "gso",
    "russian": "1) буд. вр. от འཚོ་བ; 2) см. གསོ་བ"
  },
  {
    "tibetan": "གསོ་དཀའ་བ",
    "wylie": "gso dka' ba",
    "english": "difficult to cure.",
    "russian": "трудноизлечимый"
  },
  {
    "tibetan": "གསོ་སྐྱོང་བྱེད་པ",
    "wylie": "gso skyong byed pa",
    "english": "to foster; to train; to breed.",
    "russian": "воспитывать, взращивать; готовить (кадры); держать (животных)"
  },
  {
    "tibetan": "གསོ་བསྐྲུན་པ",
    "wylie": "gso bskrun pa",
    "english": "to build.",
    "russian": "строить"
  },
  {
    "tibetan": "གསོ་མཁན",
    "wylie": "gso mkhan",
    "english": "1) cherisher, fosterer; 2) restorer.",
    "russian": "1) заботящийся, воспитывающий; 2) реставратор"
  },
  {
    "tibetan": "གསོ་ཐབས",
    "wylie": "gso thabs",
    "english": "method of curing.",
    "russian": "метод (способ) лечения"
  },
  {
    "tibetan": "གསོ་ཐིགས",
    "wylie": "gso thigs",
    "english": "cure-drop.",
    "russian": "лечебные капли"
  },
  {
    "tibetan": "གསོ་དཔྱད་མཁན",
    "wylie": "gso dpyad mkhan",
    "english": "doctor, physician.",
    "russian": "умеющий лечить, лекарь, врач",
    "sanskrit": "cikitsaka"
  },
  {
    "tibetan": "གསོ་དཔྱད་པ",
    "wylie": "gso dpyad pa",
    "english": "see above.",
    "russian": "см. выше"
  },
  {
    "tibetan": "གསོ་སྐྱོང",
    "wylie": "gso skyong",
    "english": "1) the work of healing; 2) nourishing, bringing up, rearing.",
    "russian": "1) лечение; 2) воспитание, вскармливание"
  },
  {
    "tibetan": "གསོ་བ",
    "wylie": "gso ba",
    "english": "to feed, to foster, to nourish; to train; to bread; to bring up a child; 2) to cure; to mend; to repair; to repair a house; to console, to cheer up.",
    "russian": "прош. вр. གསོས་ и བསོས 1) кормить, вскармливать, воспитывать; готовить (кадры); держать, выкармливать (скот); བུ་གསོ་བ воспитывать ребёнка; 2) лечить; чинить, ремонтировать; ཁྱིམ་གསོ་བ ремонтировать дом; སེམས་གསོ་བ утешать, ободрять"
  },
  {
    "tibetan": "གསོ་བོ",
    "wylie": "gso bo",
    "english": "1) cherisher; fosterer; 2) met. father; parents; 3) met. physician.",
    "russian": "1) заботящийся; воспитывающий; 2) перен. отец; родители; 3) перен. врач"
  },
  {
    "tibetan": "གསོ་བ་རིག་པ",
    "wylie": "gso ba rig pa",
    "english": "medicine.",
    "russian": "медицина",
    "sanskrit": "cikitsā-vidyā"
  },
  {
    "tibetan": "གསོ་བའི་སྐར་མ",
    "wylie": "gso ba'i skar ma",
    "english": "the constellation of Revatī.",
    "russian": "созвездие Ревати",
    "sanskrit": "revatīnakṣatra"
  },
  {
    "tibetan": "གསོ་བྱ",
    "wylie": "gso bya",
    "english": "the thing to be cured, disease.",
    "russian": "подлежащее лечению, болезнь"
  },
  {
    "tibetan": "གསོ་བྱེད",
    "wylie": "gso byed",
    "english": "\"healing; nourishing, feeding\"; a) doctor, physician; b) remedy; c) agriculture; d) dog; e) domestic fowl; f) the Indian mulberry tree.",
    "russian": "\"лечащий; воспитывающий, кормящий\"; а) лекарь, врач; б) лекарство; в) земледелие; г) собака; д) домашняя птица; е) индийская шелковица"
  },
  {
    "tibetan": "གསོ་སྦྱོང",
    "wylie": "gso sbyong",
    "english": "buddh. poṣadha (the rite of repentance and renewal of vows or renunciations); \"basis of poṣadha\" (the first two groups of renunciations consisting of the seventeen opening vows of the Vinaya).",
    "russian": "будд. пошадха (обряд покаяния и возобновления обетов или отречений); གསོ་སྦྱོང་གཞི \"основа пошадхи\" (первые две категории отречений, включающих 17 начальных обетов Винаи)",
    "sanskrit": "poṣadha"
  },
  {
    "tibetan": "གསོ་སྦྱོང་བ",
    "wylie": "gso sbyong ba",
    "english": "performing the rite of repentance and renewal of vows.",
    "russian": "совершающий обряд покаяния и возобновления обетов"
  },
  {
    "tibetan": "གསོ་སྦྱོང་འཕགས",
    "wylie": "gso sbyong 'phags",
    "english": "n. of an ancestor of Gautama Buddha.",
    "russian": "имя одного из предков Будды",
    "sanskrit": "upoṣadha"
  },
  {
    "tibetan": "གསོ་སྐྱོང་བྱེད་པ",
    "wylie": "gso skyong byed pa",
    "english": "to train (specialists); ལས་བྱེད་པ་མང་པོ་གསོ་སྐྱོང་བྱེད་པ to prepare qualified personnel.",
    "russian": "готовить (кадры); ལས་བྱེད་པ་མང་པོ་གསོ་སྐྱོང་བྱེད་པ готовить квалифицированные кадры"
  },
  {
    "tibetan": "གསོས",
    "wylie": "gsos",
    "english": "hamp; flax;",
    "russian": "конопля; лён; གསོས་རས་ холщовая",
    "continues_next_page": true
  }
]