[
  {
    "tibetan": " སྲོག་སྐྱོབ",
    "wylie": " srog skyob",
    "english": " deliverer, redeemer.",
    "russian": " спаситель, избавитель"
  },
  {
    "tibetan": " སྲོག་ཁུང",
    "wylie": " srog khung",
    "english": " 1) the hole through which life passes away; 2) the deep cut (by which Tibetan butcher kill animals); སྲོག་ཁུང་འབྱེད་པ to stab.",
    "russian": " 1) отверстие, через которое уходит жизнь; 2) глубокая рана (наносимая мясником, закалываемому животному); སྲོག་ཁུང་འབྱེད་པ убивать, закалывать"
  },
  {
    "tibetan": " སྲོག་གི་གུར",
    "wylie": " srog gi gur",
    "english": " poet. vein.",
    "russian": " поэт. кровеносный сосуд"
  },
  {
    "tibetan": " སྲོག་གི་གནས",
    "wylie": " srog gi gnas",
    "english": " poet. heart.",
    "russian": " поэт. сердце"
  },
  {
    "tibetan": " སྲོག་གི་དབང་པོ",
    "wylie": " srog gi dbang po",
    "english": " see above.",
    "russian": " см. выше"
  },
  {
    "tibetan": " སྲོག་གི་མེ་ཏོག",
    "wylie": " srog gi me tog",
    "english": " \"the flower of life\" (see ཚེ་མདུད).",
    "russian": " \"цветок жизни\" (см. ཚེ་མདུད)"
  },
  {
    "tibetan": " སྲོག་འགྲོ",
    "wylie": " srog 'gro",
    "english": " death.",
    "russian": " смерть"
  },
  {
    "tibetan": " སྲོག་ཅན",
    "wylie": " srog can",
    "english": " living being; alive.",
    "russian": " живое существо; живой"
  },
  {
    "tibetan": " སྲོག་གཅོད་པ",
    "wylie": " srog gcod pa",
    "english": " 1. to take one's life, to kill; 2. taking the life, killing; སྲོག་གཅོད་པའི་ལས་བྱེད་པ butcher, slaughterer; སྲོག་གཅོད་པ་སྤངས་པ buddh. abstinence from taking one's life.",
    "russian": " 1. лишать жизни, убивать; 2. лишение жизни, убийство; སྲོག་གཅོད་པའི་ལས་བྱེད་པ мясник; སྲོག་གཅོད་པ་སྤངས་པ будд. отказ от лишения жизни",
    "sanskrit": " prāṇātighāta, prāṇātipāta-virati"
  },
  {
    "tibetan": " སྲོག་ཆགས",
    "wylie": " srog chags",
    "english": " 1) animated (living) being; 2) insect.",
    "russian": " 1) одушевлённое (живое) существо; 2) насекомое",
    "sanskrit": " prāṇin, prāṇaka, prāṇī"
  },
  {
    "tibetan": " སྲོག་ཆགས་ཀིཉྩུ་ལུ་ཀ",
    "wylie": " srog chags ki nytsu lu ka",
    "english": " rainworm.",
    "russian": " дождевой червь",
    "sanskrit": " kiñculaka"
  },
  {
    "tibetan": " སྲོག་ཆགས་རྐང་མང",
    "wylie": " srog chags rkang mang",
    "english": " myriapod.",
    "russian": " зоол. многоножка"
  },
  {
    "tibetan": " སྲོག་ཆགས་ལྡན",
    "wylie": " srog chags ldan",
    "english": " living being; alive.",
    "russian": " живое существо; живой"
  },
  {
    "tibetan": " སྲོག་ཆགས་ལྡུམ་མ",
    "wylie": " srog chags ldum ma",
    "english": " poet. pregnant.",
    "russian": " поэт. беременная"
  },
  {
    "tibetan": " སྲོག་ཆགས་སྦྲང་མ",
    "wylie": " srog chags sbrang ma",
    "english": " insects.",
    "russian": " насекомые"
  },
  {
    "tibetan": " སྲོག་ཆགས་མུག་པ",
    "wylie": " srog chags mug pa",
    "english": " moth.",
    "russian": " моль"
  },
  {
    "tibetan": " སྲོག་ཆགས་རྔོན་པ",
    "wylie": " srog chags rngon pa",
    "english": " to hunt, to pursuit game.",
    "russian": " охотиться, преследовать дичь"
  },
  {
    "tibetan": " སྲོག་ཆགས་རིག་པ",
    "wylie": " srog chags rig pa",
    "english": " entomology.",
    "russian": " энтомология"
  },
  {
    "tibetan": " སྲོག་ཆགས་རིང་པོ",
    "wylie": " srog chags ring po",
    "english": " rainworm.",
    "russian": " дождевой червь"
  },
  {
    "tibetan": " སྲོག་ཆད་པ",
    "wylie": " srog chad pa",
    "english": " death.",
    "russian": " смерть"
  },
  {
    "tibetan": " སྲོག་ཉེན",
    "wylie": " srog nyen",
    "english": " danger for life; perdition; སྲོག་ཉེན་ལས་སྐྱོབ to escape perdition.",
    "russian": " опасность для жизни; гибель; སྲོག་ཉེན་ལས་སྐྱོབ спастись от гибели"
  },
  {
    "tibetan": " སྲོག་རྟེན",
    "wylie": " srog rten",
    "english": " poet. heart.",
    "russian": " поэт. сердце"
  },
  {
    "tibetan": " སྲོག་ཐག",
    "wylie": " srog thag",
    "english": " rope to hang a person.",
    "russian": " верёвка, на которой вешают осуждённого (букв. веревка, [отнимающая] жизнь)"
  },
  {
    "tibetan": " སྲོག་ཐོག་གི་ཉེས་པ་གཅོད་པ",
    "wylie": " srog thog gi nyes pa gcod pa",
    "english": " to pass sentence of death.",
    "russian": " выносить смертный приговор"
  },
  {
    "tibetan": " སྲོག་མཐར་བྱེད",
    "wylie": " srog mthar byed",
    "english": " buddh. to take one's life, to kill.",
    "russian": " будд. лишать жизни, убивать"
  },
  {
    "tibetan": " སྲོག་དང་བསམ་པ",
    "wylie": " srog dang bsam pa",
    "english": " intention.",
    "russian": " намерение",
    "sanskrit": " cetanā"
  },
  {
    "tibetan": " སྲོག་དང་བསྡོ་བ",
    "wylie": " srog dang bsdo ba",
    "english": " to risk (hazard) one's life.",
    "russian": " рисковать жизнью"
  },
  {
    "tibetan": " སྲོག་དང་འབྲལ་བ",
    "wylie": " srog dang 'bral ba",
    "english": " to execute, to put to death.",
    "russian": " убивать, умерщвлять"
  },
  {
    "tibetan": " སྲོག་དོར་འབྲལ་བ",
    "wylie": " srog dor 'bral ba",
    "english": " to die.",
    "russian": " умирать"
  },
  {
    "tibetan": " སྲོག་དོར་བ",
    "wylie": " srog dor ba",
    "english": " deceased.",
    "russian": " умерший"
  },
  {
    "tibetan": " སྲོག་བདག་ཆེན་པོ",
    "wylie": " srog bdag chen po",
    "english": " \"the Great lord of life\" (epith. of the guardian deity of the monastery of Sam-ye).",
    "russian": " \"Великий владыка жизни\" (эпит. охраняющего божества монастыря Самье, см. པེ་ཧར)"
  },
  {
    "tibetan": " སྲོག་འདོར",
    "wylie": " srog 'dor",
    "english": " death.",
    "russian": " смерть"
  },
  {
    "tibetan": " སྲོག་འདོར་བ",
    "wylie": " srog 'dor ba",
    "english": " to sacrifice one's life.",
    "russian": " отдавать жизнь, жертвовать жизнью"
  },
  {
    "tibetan": " སྲོག་ལྡན",
    "wylie": " srog ldan",
    "english": " living being; alive.",
    "russian": " живое существо, живой"
  },
  {
    "tibetan": " སྲོག་གནས",
    "wylie": " srog gnas",
    "english": " poet. heart (lit. residence of life).",
    "russian": " поэт. сердце (букв. местопребывание жизни)"
  }
]